kmtm/__init__.py
kmtm/cli.py
kmtm-0.1.2.dist-info/LICENSE
kmtm-0.1.2.dist-info/METADATA
kmtm-0.1.2.dist-info/WHEEL
kmtm-0.1.2.dist-info/entry_points.txt
kmtm-0.1.2.dist-info/top_level.txt
kmtm-0.1.2.dist-info/RECORD
