Metadata-Version: 2.1
Name: kmtm
Version: 0.1.2
Summary: Simple tool to convert kilometers/miles.
Home-page: https://github.com/jmaslanko/kmtm
Author: Jeremy Maslanko
Author-email: maslankoj@gmail.com
License: UNKNOWN
Platform: UNKNOWN
Classifier: Programming Language :: Python :: 3
Classifier: License :: OSI Approved :: MIT License
License-File: LICENSE
Requires-Dist: Click
